MANIFEST.in
README.rst
setup.py
bin/wrangler
wrangler/BasicServer.py
wrangler/Core.py
wrangler/Extensions.py
wrangler/JinjaStaticRenderer.py
wrangler/MarkdownExtension.py
wrangler/NewProject.py
wrangler/Parsers.py
wrangler/Reader.py
wrangler/SilentUndefined.py
wrangler/Watcher.py
wrangler/__init__.py
wrangler/defaults.py
wrangler/messages.py
wrangler/utilities.py
wrangler.egg-info/PKG-INFO
wrangler.egg-info/SOURCES.txt
wrangler.egg-info/dependency_links.txt
wrangler.egg-info/not-zip-safe
wrangler.egg-info/requires.txt
wrangler.egg-info/top_level.txt