Metadata-Version: 1.0
Name: wrangler
Version: 0.1.8.3
Summary: A pythonic static site generator
Home-page: http://github.com/springload/Wrangler.py
Author: Springload
Author-email: hello@springload.co.nz
License: MIT
Platform: UNKNOWN
